{
    "type": "box",
    "id": "17564",
    "name": "[일반SSS][9강 기회] 25TOTS 상자",
    "image": null,
    "expectedBp": 11381933508738.334,
    "expectedValue": {
        "bp_player": 11381933508738.334
    },
    "expectedBp1": 11381933508738.334,
    "expectedValue1": {
        "bp_player": 11381933508738.334
    },
    "percentile": {
        "0": 3450000000000000,
        "1": 89000000000000,
        "2": 67500000000000,
        "5": 37500000000000,
        "10": 18100000000000,
        "20": 10000000000000,
        "30": 8280000000000,
        "40": 7230000000000,
        "50": 6710000000000,
        "60": 6360000000000,
        "70": 5420000000000,
        "80": 4680000000000,
        "90": 4110000000000,
        "100": 2440000000000
    },
    "itemList": [
        {
            "item": {
                "type": "player-pack",
                "id": "17523",
                "name": "25TOTS Top Price 150 선수팩 (9강, 116+)",
                "image": null,
                "expectedBp": 114426729694886.19,
                "expectedValue": {
                    "bp_player": 114426729694886.19
                }
            },
            "amount": 1,
            "probability": 0.003
        },
        {
            "item": {
                "type": "player-pack",
                "id": "17524",
                "name": "25TOTS Top Price 150 선수팩 (8강, 116+)",
                "image": null,
                "expectedBp": 59385542168674.7,
                "expectedValue": {
                    "bp_player": 59385542168674.7
                }
            },
            "amount": 1,
            "probability": 0.025
        },
        {
            "item": {
                "type": "player-pack",
                "id": "17482",
                "name": "25TOTS Top Price 140 선수팩 (7강, 116+)",
                "image": null,
                "expectedBp": 12481680365296.8,
                "expectedValue": {
                    "bp_player": 12481680365296.8
                }
            },
            "amount": 1,
            "probability": 0.467
        },
        {
            "item": {
                "type": "player-pack",
                "id": "17481",
                "name": "25TOTS Top Price 120 선수팩 (5~6강, 118+)",
                "image": null,
                "expectedBp": 7376376306620.201,
                "expectedValue": {
                    "bp_player": 7376376306620.201
                }
            },
            "amount": 1,
            "probability": 0.505
        }
    ],
    "additionalInfoWithAmount": null
}