{
    "type": "box",
    "id": "18008",
    "name": "[열쇠 60개] 싱글드로우 상자",
    "image": null,
    "expectedBp": 97334915109683.89,
    "expectedValue": {
        "bp_player": 86122415109683.89,
        "bp_card": 11212500000000.0
    },
    "expectedBp1": 97334915109683.89,
    "expectedValue1": {
        "bp_player": 86122415109683.89,
        "bp_card": 11212500000000.0
    },
    "percentile": {
        "0": 11000000000000000,
        "1": 228000000000000,
        "2": 212000000000000,
        "5": 198000000000000,
        "10": 188000000000000,
        "20": 162000000000000,
        "30": 143000000000000,
        "40": 122000000000000,
        "50": 97800000000000,
        "60": 61400000000000,
        "70": 28000000000000,
        "80": 28000000000000,
        "90": 28000000000000,
        "100": 28000000000000
    },
    "itemList": [
        {
            "item": {
                "type": "player-pack",
                "id": "17980",
                "name": "[열쇠 60개] 25TOTS 포함 Top Price 880 (10강, 104+)",
                "image": null,
                "expectedBp": 198040336554860.75,
                "expectedValue": {
                    "bp_player": 198040336554860.75
                }
            },
            "amount": 1,
            "probability": 0.006999999999999999
        },
        {
            "item": {
                "type": "player-pack",
                "id": "17981",
                "name": "[열쇠 60개] 25TOTS 포함 Top Price 990 (9강, 105+)",
                "image": null,
                "expectedBp": 131815614059118.84,
                "expectedValue": {
                    "bp_player": 131815614059118.84
                }
            },
            "amount": 1,
            "probability": 0.035
        },
        {
            "item": {
                "type": "player-pack",
                "id": "18016",
                "name": "[열쇠 60개] 25TOTS 포함 8강 선수팩 (최종 OVR 126+)",
                "image": null,
                "expectedBp": 141060891305863.94,
                "expectedValue": {
                    "bp_player": 141060891305863.94
                }
            },
            "amount": 1,
            "probability": 0.568
        },
        {
            "item": {
                "type": "bp",
                "id": "18000",
                "name": "[열쇠 60개] 행운의 BP 카드 (28조~55조)",
                "image": null,
                "expectedBp": 28750000000000.0,
                "expectedValue": {
                    "bp_card": 28750000000000.0
                }
            },
            "amount": 1,
            "probability": 0.39
        }
    ],
    "additionalInfoWithAmount": null
}