{
    "type": "box",
    "id": "18732",
    "name": "[AG][25TOTS 찬스] 25IM-S&P 프리미엄 의뢰 상자",
    "image": null,
    "expectedBp": 1432840990534.4893,
    "expectedValue": {
        "bp_player": 1432840990534.4893
    },
    "expectedBp1": 1432840990534.4893,
    "expectedValue1": {
        "bp_player": 1432840990534.4893
    },
    "percentile": {
        "0": 3740000000000000,
        "1": 14200000000000,
        "2": 7150000000000,
        "5": 2160000000000,
        "10": 1210000000000,
        "20": 978000000000,
        "30": 937000000000,
        "40": 847000000000,
        "50": 801000000000,
        "60": 747000000000,
        "70": 720000000000,
        "80": 712000000000,
        "90": 658000000000,
        "100": 583000000000
    },
    "itemList": [
        {
            "item": {
                "type": "player-pack",
                "id": "18579",
                "name": "[AG] 프리미엄 25TOTS 클래스 Top Price ALL 선수팩 (8강)",
                "image": null,
                "expectedBp": 65367030956749.36,
                "expectedValue": {
                    "bp_player": 65367030956749.36
                }
            },
            "amount": 1,
            "probability": 0.002
        },
        {
            "item": {
                "type": "player-pack",
                "id": "18583",
                "name": "[AG][MDL 포함] 멀티 클래스 Top Price 450 스페셜팩 (8강)",
                "image": null,
                "expectedBp": 1423559169048.6724,
                "expectedValue": {
                    "bp_player": 1423559169048.6724
                }
            },
            "amount": 1,
            "probability": 0.39799999999999996
        },
        {
            "item": {
                "type": "player-pack",
                "id": "18584",
                "name": "[AG][BDO 포함] 멀티 클래스 Top Price 900 스페셜팩 (1~7강)",
                "image": null,
                "expectedBp": 1225883965566.0312,
                "expectedValue": {
                    "bp_player": 1225883965566.0312
                }
            },
            "amount": 1,
            "probability": 0.6
        }
    ],
    "additionalInfoWithAmount": null
}