{
    "type": "box",
    "id": "18735",
    "name": "[AG][특수 클래스 한정][25.08] 스페셜 에이전트 의뢰 2 리워드 상자",
    "image": null,
    "expectedBp": 83631431654.11487,
    "expectedValue": {
        "bp_player": 57326629983.96875,
        "bp_card": 26304801670.146126
    },
    "expectedBp1": 83631431654.11487,
    "expectedValue1": {
        "bp_player": 57326629983.96875,
        "bp_card": 26304801670.146126
    },
    "percentile": {
        "0": 1660000000000000,
        "1": 250000000000,
        "2": 226000000000,
        "5": 192000000000,
        "10": 147000000000,
        "20": 92200000000,
        "30": 83900000000,
        "40": 75200000000,
        "50": 70700000000,
        "60": 65600000000,
        "70": 60000000000,
        "80": 48700000000,
        "90": 44600000000,
        "100": 17800000000
    },
    "itemList": [
        {
            "item": {
                "type": "player-pack",
                "id": "18587",
                "name": "[AG][MDL 포함] 멀티 클래스 Top Price 1000 선수팩 (8강, 100+)",
                "image": null,
                "expectedBp": 465934477779.8153,
                "expectedValue": {
                    "bp_player": 465934477779.8153
                }
            },
            "amount": 1,
            "probability": 0.0001
        },
        {
            "item": {
                "type": "player-pack",
                "id": "18589",
                "name": "[AG][LE 3~5강 포함] 멀티 클래스 최종 OVR 115+ 선수팩 (3~7강)",
                "image": null,
                "expectedBp": 88136692623.77408,
                "expectedValue": {
                    "bp_player": 88136692623.77408
                }
            },
            "amount": 1,
            "probability": 0.6498999999999999
        },
        {
            "item": {
                "type": "bp",
                "id": "18607",
                "name": "[AG] 행운의 BP 카드 (450억~5000억 BP)",
                "image": null,
                "expectedBp": 75156576200.41751,
                "expectedValue": {
                    "bp_card": 75156576200.41751
                }
            },
            "amount": 1,
            "probability": 0.35
        }
    ],
    "additionalInfoWithAmount": null
}