{
    "type": "box",
    "id": "19837",
    "name": "[EBS GK 10강 포함] 스쿼드 패스 상자 (50pt)",
    "image": null,
    "expectedBp": 255589666341.25916,
    "expectedValue": {
        "bp_player": 185596665641.32916,
        "[MASTER] 마스터 키 (~2026.01.14)": 9.99900009999e-05,
        "bp_card": 69993000699.93
    },
    "expectedBp1": 255589666341.25916,
    "expectedValue1": {
        "bp_player": 185596665641.32916,
        "[MASTER] 마스터 키 (~2026.01.14)": 9.99900009999e-05,
        "bp_card": 69993000699.93
    },
    "percentile": {
        "0": 2620000000000000,
        "1": 1700000000000,
        "2": 1300000000000,
        "5": 442000000000,
        "10": 360000000000,
        "20": 282000000000,
        "30": 205000000000,
        "40": 200000000000,
        "50": 200000000000,
        "60": 150000000000,
        "70": 150000000000,
        "80": 138000000000,
        "90": 95000000000,
        "100": 0
    },
    "itemList": [
        {
            "item": {
                "type": "player-pack",
                "id": "19803",
                "name": "[스쿼드 패스] EBS 포함 GK 스페셜팩 (8~10강, 78+)",
                "image": null,
                "expectedBp": 10551656827647.383,
                "expectedValue": {
                    "bp_player": 10551656827647.383
                }
            },
            "amount": 1,
            "probability": 9.99900009999e-05
        },
        {
            "item": {
                "type": "other",
                "id": -1,
                "name": "[MASTER] 마스터 키 (~2026.01.14)",
                "image": null,
                "expectedBp": 0,
                "expectedValue": {
                    "[MASTER] 마스터 키 (~2026.01.14)": 1
                }
            },
            "amount": 1,
            "probability": 9.99900009999e-05
        },
        {
            "item": {
                "type": "player-pack",
                "id": "19819",
                "name": "[스쿼드 패스] MDL 포함 Top Price 450 스페셜팩 (8강, 102+)",
                "image": null,
                "expectedBp": 3767085305632.089,
                "expectedValue": {
                    "bp_player": 3767085305632.089
                }
            },
            "amount": 1,
            "probability": 0.0098990100989901
        },
        {
            "item": {
                "type": "player-pack",
                "id": "19808",
                "name": "[BDO 포함] Top Price 2000 스페셜팩 (5~7강, 103+)",
                "image": null,
                "expectedBp": 455209699580.03613,
                "expectedValue": {
                    "bp_player": 455209699580.03613
                }
            },
            "amount": 1,
            "probability": 0.08999100089991
        },
        {
            "item": {
                "type": "player-pack",
                "id": "19813",
                "name": "[24UCL 5~7강 포함] 최종 OVR 118+ 스페셜팩 (5~8강)",
                "image": null,
                "expectedBp": 342603466321.24744,
                "expectedValue": {
                    "bp_player": 342603466321.24744
                }
            },
            "amount": 1,
            "probability": 0.1999800019998
        },
        {
            "item": {
                "type": "bp",
                "id": "19821",
                "name": "BP 카드 200,000,000,000",
                "image": null,
                "expectedBp": 200000000000.0,
                "expectedValue": {
                    "bp_card": 200000000000.0
                }
            },
            "amount": 1,
            "probability": 0.1999800019998
        },
        {
            "item": {
                "type": "player-pack",
                "id": "19814",
                "name": "[GRU 3~7강 포함] 최종 OVR 116+ 스페셜팩 (3~8강)",
                "image": null,
                "expectedBp": 133281597311.1615,
                "expectedValue": {
                    "bp_player": 133281597311.1615
                }
            },
            "amount": 1,
            "probability": 0.1999800019998
        },
        {
            "item": {
                "type": "bp",
                "id": "19822",
                "name": "BP 카드 150,000,000,000",
                "image": null,
                "expectedBp": 150000000000.0,
                "expectedValue": {
                    "bp_card": 150000000000.0
                }
            },
            "amount": 1,
            "probability": 0.1999800019998
        },
        {
            "item": {
                "type": "player-pack",
                "id": "19815",
                "name": "[BDO 3~7강 포함] 최종 OVR 115+ 스페셜팩 (3~8강)",
                "image": null,
                "expectedBp": 111200294106.85869,
                "expectedValue": {
                    "bp_player": 111200294106.85869
                }
            },
            "amount": 1,
            "probability": 0.0999900009999
        }
    ],
    "additionalInfoWithAmount": null
}