{
    "type": "box",
    "id": "20109",
    "name": "[일반SSS][10강 포함] 상자",
    "image": null,
    "expectedBp": 42617089109549.67,
    "expectedValue": {
        "bp_player": 42617089109549.67
    },
    "expectedBp1": 42617089109549.67,
    "expectedValue1": {
        "bp_player": 42617089109549.67
    },
    "percentile": {
        "0": 18000000000000000,
        "1": 336000000000000,
        "2": 231000000000000,
        "5": 106000000000000,
        "10": 78100000000000,
        "20": 49100000000000,
        "30": 38500000000000,
        "40": 29700000000000,
        "50": 25700000000000,
        "60": 21400000000000,
        "70": 17700000000000,
        "80": 15600000000000,
        "90": 14600000000000,
        "100": 12900000000000
    },
    "itemList": [
        {
            "item": {
                "type": "player-pack",
                "id": "20074",
                "name": "25HEROES 포함 Top Price 580 선수팩 (10강, 108+)",
                "image": null,
                "expectedBp": 136285566316922.28,
                "expectedValue": {
                    "bp_player": 136285566316922.28
                }
            },
            "amount": 1,
            "probability": 0.03
        },
        {
            "item": {
                "type": "player-pack",
                "id": "20075",
                "name": "CH, DCB Top Price 140 선수팩 (8강, 113+)",
                "image": null,
                "expectedBp": 109664830321727.7,
                "expectedValue": {
                    "bp_player": 109664830321727.7
                }
            },
            "amount": 1,
            "probability": 0.04
        },
        {
            "item": {
                "type": "player-pack",
                "id": "20076",
                "name": "NO.7, LE, WB 포함 Top Price 540 선수팩 (9강, 108+)",
                "image": null,
                "expectedBp": 42906899151743.625,
                "expectedValue": {
                    "bp_player": 42906899151743.625
                }
            },
            "amount": 1,
            "probability": 0.31
        },
        {
            "item": {
                "type": "player-pack",
                "id": "20077",
                "name": "NO.7, LE, WB 포함 Top Price 390 선수팩 (8강, 113+)",
                "image": null,
                "expectedBp": 33614177693761.9,
                "expectedValue": {
                    "bp_player": 33614177693761.9
                }
            },
            "amount": 1,
            "probability": 0.62
        }
    ],
    "additionalInfoWithAmount": null
}