{
    "type": "box",
    "id": "20109",
    "name": "[일반SSS][10강 포함] 상자",
    "image": null,
    "expectedBp": 43865908916522.06,
    "expectedValue": {
        "bp_player": 43865908916522.06
    },
    "expectedBp1": 43865908916522.06,
    "expectedValue1": {
        "bp_player": 43865908916522.06
    },
    "percentile": {
        "0": 18600000000000000,
        "1": 340000000000000,
        "2": 236000000000000,
        "5": 110000000000000,
        "10": 79300000000000,
        "20": 47600000000000,
        "30": 39500000000000,
        "40": 31900000000000,
        "50": 26600000000000,
        "60": 23200000000000,
        "70": 19200000000000,
        "80": 16900000000000,
        "90": 15200000000000,
        "100": 13800000000000
    },
    "itemList": [
        {
            "item": {
                "type": "player-pack",
                "id": "20074",
                "name": "25HEROES 포함 Top Price 580 선수팩 (10강, 108+)",
                "image": null,
                "expectedBp": 136118778584880.31,
                "expectedValue": {
                    "bp_player": 136118778584880.31
                }
            },
            "amount": 1,
            "probability": 0.03
        },
        {
            "item": {
                "type": "player-pack",
                "id": "20075",
                "name": "CH, DCB Top Price 140 선수팩 (8강, 113+)",
                "image": null,
                "expectedBp": 113541868664610.03,
                "expectedValue": {
                    "bp_player": 113541868664610.03
                }
            },
            "amount": 1,
            "probability": 0.04
        },
        {
            "item": {
                "type": "player-pack",
                "id": "20076",
                "name": "NO.7, LE, WB 포함 Top Price 540 선수팩 (9강, 108+)",
                "image": null,
                "expectedBp": 43740301602262.0,
                "expectedValue": {
                    "bp_player": 43740301602262.0
                }
            },
            "amount": 1,
            "probability": 0.31
        },
        {
            "item": {
                "type": "player-pack",
                "id": "20077",
                "name": "NO.7, LE, WB 포함 Top Price 390 선수팩 (8강, 113+)",
                "image": null,
                "expectedBp": 34969640831758.11,
                "expectedValue": {
                    "bp_player": 34969640831758.11
                }
            },
            "amount": 1,
            "probability": 0.62
        }
    ],
    "additionalInfoWithAmount": null
}