{
    "type": "box",
    "id": "21179",
    "name": "[5~8강] 26TOTY or 26TOTY-N 확정 프리미엄 상자",
    "image": "/assets/image/item/201709170_s.png",
    "expectedBp": 71851763978449.9,
    "expectedValue": {
        "bp_player": 71851763978449.9
    },
    "expectedBp1": 71851763978449.9,
    "expectedValue1": {
        "bp_player": 71851763978449.9
    },
    "percentile": {
        "0": 35000000000000000,
        "1": 426000000000000,
        "2": 259000000000000,
        "5": 155000000000000,
        "10": 112000000000000,
        "20": 101000000000000,
        "30": 78900000000000,
        "40": 54700000000000,
        "50": 43700000000000,
        "60": 38700000000000,
        "70": 36300000000000,
        "80": 30100000000000,
        "90": 26200000000000,
        "100": 17000000000000
    },
    "itemList": [
        {
            "item": {
                "type": "player-pack",
                "id": "21143",
                "name": "26TOTY Top Price All (8강)",
                "image": null,
                "expectedBp": 3767743859395961.0,
                "expectedValue": {
                    "bp_player": 3767743859395961.0
                }
            },
            "amount": 1,
            "probability": 0.0001
        },
        {
            "item": {
                "type": "player-pack",
                "id": "21144",
                "name": "26TOTY-N Top Price All (8강)",
                "image": null,
                "expectedBp": 574964308589080.9,
                "expectedValue": {
                    "bp_player": 574964308589080.9
                }
            },
            "amount": 1,
            "probability": 0.001
        },
        {
            "item": {
                "type": "player-pack",
                "id": "21145",
                "name": "26TOTY Top Price All (7강)",
                "image": null,
                "expectedBp": 496240663249345.6,
                "expectedValue": {
                    "bp_player": 496240663249345.6
                }
            },
            "amount": 1,
            "probability": 0.026489
        },
        {
            "item": {
                "type": "player-pack",
                "id": "21146",
                "name": "26TOTY-N Top Price 65 (7강, 116+)",
                "image": null,
                "expectedBp": 58335917437943.89,
                "expectedValue": {
                    "bp_player": 58335917437943.89
                }
            },
            "amount": 1,
            "probability": 0.26834399999999997
        },
        {
            "item": {
                "type": "player-pack",
                "id": "21147",
                "name": "26TOTY Top Price All (5~6강)",
                "image": null,
                "expectedBp": 85009491588773.66,
                "expectedValue": {
                    "bp_player": 85009491588773.66
                }
            },
            "amount": 1,
            "probability": 0.14180500000000001
        },
        {
            "item": {
                "type": "player-pack",
                "id": "21148",
                "name": "26TOTY-N Top Price 44 (5~6강, 116+)",
                "image": null,
                "expectedBp": 53438151558162.64,
                "expectedValue": {
                    "bp_player": 53438151558162.64
                }
            },
            "amount": 1,
            "probability": 0.562262
        }
    ],
    "additionalInfoWithAmount": null
}