{
    "type": "box",
    "id": "21568",
    "name": "[열쇠 120개] 더블드로우 상자 (02.20)",
    "image": null,
    "expectedBp": 2652790593432875.5,
    "expectedValue": {
        "bp_player": 2652790593432875.5
    },
    "expectedBp1": 2652790593432875.5,
    "expectedValue1": {
        "bp_player": 2652790593432875.5
    },
    "percentile": {
        "0": 65200000000000000,
        "1": 4560000000000000,
        "2": 4190000000000000,
        "5": 3700000000000000,
        "10": 3590000000000000,
        "20": 3170000000000000,
        "30": 2900000000000000,
        "40": 2700000000000000,
        "50": 2600000000000000,
        "60": 2390000000000000,
        "70": 2280000000000000,
        "80": 2080000000000000,
        "90": 1930000000000000,
        "100": 1600000000000000
    },
    "itemList": [
        {
            "item": {
                "type": "box",
                "id": "21620",
                "name": "[열쇠 120개] 25UCL 9강팩 + LE 포함 10강팩 상자 (02.20)",
                "image": null,
                "expectedBp": 3794223654665447.5,
                "expectedValue": {
                    "bp_player": 3794223654665447.5
                }
            },
            "amount": 1,
            "probability": 0.015371999999999999
        },
        {
            "item": {
                "type": "box",
                "id": "21621",
                "name": "[열쇠 120개] 25UCL 8강팩 + LE 포함 10강팩 상자 (02.20)",
                "image": null,
                "expectedBp": 3407914277313278.0,
                "expectedValue": {
                    "bp_player": 3407914277313278.0
                }
            },
            "amount": 1,
            "probability": 0.09042299999999999
        },
        {
            "item": {
                "type": "player-pack",
                "id": "21603",
                "name": "[열쇠 120개] BDO, BLD 포함 Top Price 290 (11강, 107+)",
                "image": null,
                "expectedBp": 2427571632326866.0,
                "expectedValue": {
                    "bp_player": 2427571632326866.0
                }
            },
            "amount": 1,
            "probability": 0.097121
        },
        {
            "item": {
                "type": "player-pack",
                "id": "21604",
                "name": "[열쇠 120개] 26TOTY 포함 Top Price 80 (8강, 114+)",
                "image": null,
                "expectedBp": 2567715472192513.0,
                "expectedValue": {
                    "bp_player": 2567715472192513.0
                }
            },
            "amount": 1,
            "probability": 0.101287
        },
        {
            "item": {
                "type": "player-pack",
                "id": "21605",
                "name": "[열쇠 120개] 26TOTY-N 포함 Top Price 105 (8강, 114+)",
                "image": null,
                "expectedBp": 2573261415586269.0,
                "expectedValue": {
                    "bp_player": 2573261415586269.0
                }
            },
            "amount": 1,
            "probability": 0.695797
        }
    ],
    "additionalInfoWithAmount": null
}