{
    "type": "box",
    "id": "21704",
    "name": "[FAC TP 150 8강 찬스][26.02] 프리미엄 에이전트 의뢰 상자",
    "image": null,
    "expectedBp": 30673006577003.71,
    "expectedValue": {
        "bp_player": 15608100086354.656,
        "bp_card": 15064906490649.057
    },
    "expectedBp1": 30673006577003.71,
    "expectedValue1": {
        "bp_player": 15608100086354.656,
        "bp_card": 15064906490649.057
    },
    "percentile": {
        "0": 29300000000000000,
        "1": 109000000000000,
        "2": 70800000000000,
        "5": 60000000000000,
        "10": 45000000000000,
        "20": 36000000000000,
        "30": 32200000000000,
        "40": 28300000000000,
        "50": 26000000000000,
        "60": 22700000000000,
        "70": 20900000000000,
        "80": 18800000000000,
        "90": 17600000000000,
        "100": 13200000000000
    },
    "itemList": [
        {
            "item": {
                "type": "player-pack",
                "id": "21680",
                "name": "[AG] FAC 클래스 Top Price 150 선수팩 (8강)",
                "image": null,
                "expectedBp": 97291234401349.11,
                "expectedValue": {
                    "bp_player": 97291234401349.11
                }
            },
            "amount": 1,
            "probability": 0.001
        },
        {
            "item": {
                "type": "player-pack",
                "id": "21681",
                "name": "[AG] 25UCL, FAC, 25DP, LE 클래스 최종 OVR 128+ 선수팩 (5~8강)",
                "image": null,
                "expectedBp": 25894505595915.37,
                "expectedValue": {
                    "bp_player": 25894505595915.37
                }
            },
            "amount": 1,
            "probability": 0.599
        },
        {
            "item": {
                "type": "bp",
                "id": "21695",
                "name": "[AG] 행운의 BP 카드 (20조~500조 BP)",
                "image": null,
                "expectedBp": 37662266226622.64,
                "expectedValue": {
                    "bp_card": 37662266226622.64
                }
            },
            "amount": 1,
            "probability": 0.4
        }
    ],
    "additionalInfoWithAmount": null
}