{
    "type": "box",
    "id": "22193",
    "name": "[에센셜SSS][NO.7 10강 기회] 상자",
    "image": null,
    "expectedBp": 252121242548135.88,
    "expectedValue": {
        "bp_player": 252121242548135.88
    },
    "expectedBp1": 252121242548135.88,
    "expectedValue1": {
        "bp_player": 252121242548135.88
    },
    "percentile": {
        "0": 228000000000000000,
        "1": 800000000000000,
        "2": 579000000000000,
        "5": 422000000000000,
        "10": 366000000000000,
        "20": 319000000000000,
        "30": 264000000000000,
        "40": 230000000000000,
        "50": 204000000000000,
        "60": 179000000000000,
        "70": 161000000000000,
        "80": 146000000000000,
        "90": 129000000000000,
        "100": 80100000000000
    },
    "itemList": [
        {
            "item": {
                "type": "player-pack",
                "id": "22145",
                "name": "NO.7 포함 Top Price 930 선수팩 (10강, 109+)",
                "image": null,
                "expectedBp": 389615706928839.2,
                "expectedValue": {
                    "bp_player": 389615706928839.2
                }
            },
            "amount": 1,
            "probability": 0.05
        },
        {
            "item": {
                "type": "player-pack",
                "id": "22146",
                "name": "ICON TM Top Price 180 선수팩 (1~4강, 120+)",
                "image": null,
                "expectedBp": 411489459459459.1,
                "expectedValue": {
                    "bp_player": 411489459459459.1
                }
            },
            "amount": 1,
            "probability": 0.02
        },
        {
            "item": {
                "type": "player-pack",
                "id": "22147",
                "name": "FAC 포함 Top Price 1170 선수팩 (9강, 109+)",
                "image": null,
                "expectedBp": 247699952130206.12,
                "expectedValue": {
                    "bp_player": 247699952130206.12
                }
            },
            "amount": 1,
            "probability": 0.31
        },
        {
            "item": {
                "type": "player-pack",
                "id": "22148",
                "name": "WS 포함 Top Price 1200 선수팩 (9강, 110+)",
                "image": null,
                "expectedBp": 245197075773746.44,
                "expectedValue": {
                    "bp_player": 245197075773746.44
                }
            },
            "amount": 1,
            "probability": 0.31
        },
        {
            "item": {
                "type": "player-pack",
                "id": "22153",
                "name": "FAC 포함 Top Price 700 선수팩 (8강, 110+)",
                "image": null,
                "expectedBp": 231008352781546.62,
                "expectedValue": {
                    "bp_player": 231008352781546.62
                }
            },
            "amount": 1,
            "probability": 0.31
        }
    ],
    "additionalInfoWithAmount": null
}