{
    "type": "box",
    "id": "22427",
    "name": "[열쇠 800개] WG 9강팩 + 25UCL 포함 8~9강팩 상자",
    "image": null,
    "expectedBp": 6.563227356477192e+16,
    "expectedValue": {
        "bp_player": 6.563227356477192e+16
    },
    "expectedBp1": 6.563227356477192e+16,
    "expectedValue1": {
        "bp_player": 6.563227356477192e+16
    },
    "percentile": {
        "0": 311000000000000000,
        "1": 209000000000000000,
        "2": 203420000000000000,
        "5": 140900000000000000,
        "10": 96600000000000000,
        "20": 75000000000000000,
        "30": 68700000000000000,
        "40": 61100000000000000,
        "50": 56100000000000000,
        "60": 52000000000000000,
        "70": 49100000000000000,
        "80": 46500000000000000,
        "90": 44100000000000000,
        "100": 35720000000000000
    },
    "itemList": [
        {
            "item": {
                "type": "player-pack",
                "id": "22388",
                "name": "[열쇠 800개] WG Top Price 40 (9강, 114+)",
                "image": null,
                "expectedBp": 1.4399743444289996e+16,
                "expectedValue": {
                    "bp_player": 1.4399743444289996e+16
                }
            },
            "amount": 1,
            "probability": 1.0
        },
        {
            "item": {
                "type": "player-pack",
                "id": "22389",
                "name": "[열쇠 800개] 25UCL 포함 Top Price 12 (8~9강, 117+)",
                "image": null,
                "expectedBp": 5.123253012048192e+16,
                "expectedValue": {
                    "bp_player": 5.123253012048192e+16
                }
            },
            "amount": 1,
            "probability": 1.0
        }
    ],
    "additionalInfoWithAmount": null
}