{
    "type": "general-product",
    "id": "44507",
    "name": "[24EP 11강, FAC 9강 포함] 8~11강 선수팩 (최종 OVR 123+, 11.20 기준)",
    "image": "/assets/image/item/200231688_s.png",
    "price": 9900,
    "efficiency": 77744.59604675567,
    "expectedBp": 76967150086288.11,
    "expectedValue": {
        "bp_player": 76967150086288.11
    },
    "efficiency1": 77744.59604675567,
    "expectedBp1": 76967150086288.11,
    "expectedValue1": {
        "bp_player": 76967150086288.11
    },
    "percentile": {
        "0": 55400000000000000,
        "1": 201000000000000,
        "2": 191000000000000,
        "5": 156000000000000,
        "10": 114000000000000,
        "20": 93000000000000,
        "30": 86700000000000,
        "40": 77900000000000,
        "50": 70500000000000,
        "60": 66100000000000,
        "70": 59100000000000,
        "80": 46300000000000,
        "90": 39100000000000,
        "100": 12100000000000
    },
    "itemList": [
        {
            "item": {
                "type": "player-pack",
                "id": "20215",
                "name": "[24EP 11강, FAC 9강 포함] 8~11강 선수팩 (최종 OVR 123+, 11.20 기준)",
                "image": "/assets/image/item/200231688_s.png",
                "expectedBp": 76967150086288.11,
                "expectedValue": {
                    "bp_player": 76967150086288.11
                }
            },
            "amount": 1
        }
    ],
    "additionalInfoWithAmount": null
}