{
    "type": "general-product",
    "id": "48206",
    "name": "[FAC, 25KB 포함] 멀티클래스 Top Price 6130 (1강)",
    "image": "/assets/image/item/200235152_s.png",
    "price": 50,
    "efficiency": 6786.320236448319,
    "expectedBp": 33931601182.241592,
    "expectedValue": {
        "bp_player": 33931601182.241592
    },
    "efficiency1": 6786.320236448319,
    "expectedBp1": 33931601182.241592,
    "expectedValue1": {
        "bp_player": 33931601182.241592
    },
    "percentile": {
        "0": 7000000000000000,
        "1": 214000000000,
        "2": 210000000000,
        "5": 198000000000,
        "10": 164000000000,
        "20": 27400000000,
        "30": 3180000000,
        "40": 1010,
        "50": 1010,
        "60": 1010,
        "70": 1010,
        "80": 1010,
        "90": 1010,
        "100": 1010
    },
    "itemList": [
        {
            "item": {
                "type": "player-pack",
                "id": "21765",
                "name": "[FAC, 25KB 포함] 멀티클래스 Top Price 6130 (1강)",
                "image": "/assets/image/item/200235152_s.png",
                "expectedBp": 33931601182.241592,
                "expectedValue": {
                    "bp_player": 33931601182.241592
                }
            },
            "amount": 1
        }
    ],
    "additionalInfoWithAmount": null
}